connapi/__init__.py
connapi/connapi.py
connapi/api/__init__.py
connapi/api/agify.py
connapi/api/nasa.py
connapi/data/__init__.py
connapi-0.1.2.dist-info/AUTHORS.rst
connapi-0.1.2.dist-info/LICENSE
connapi-0.1.2.dist-info/METADATA
connapi-0.1.2.dist-info/WHEEL
connapi-0.1.2.dist-info/top_level.txt
connapi-0.1.2.dist-info/RECORD
