Metadata-Version: 2.1
Name: connapi
Version: 0.1.2
Summary: Wrapper to Use all Public Apis with single call methods
Home-page: https://github.com/YellowFoxH4XOR/connapi
Author: Akshat Katiyar
Author-email: yellowfoxh4xor@gmail.com
License: MIT license
Keywords: connapi
Platform: UNKNOWN
Classifier: Development Status :: 2 - Pre-Alpha
Classifier: Intended Audience :: Developers
Classifier: License :: OSI Approved :: MIT License
Classifier: Natural Language :: English
Classifier: Programming Language :: Python :: 3
Classifier: Programming Language :: Python :: 3.5
Classifier: Programming Language :: Python :: 3.6
Classifier: Programming Language :: Python :: 3.7
Classifier: Programming Language :: Python :: 3.8
Requires-Python: >=3.5
Requires-Dist: requests
